{
  "date": "2026-03-12",
  "updated_at": "2026-03-12 18:36 JST",
  "note_trends": [
    {
      "title": "2026年3月12日｜日経平均・東京株式市場・米国株：ポイント解説と明日の展望",
      "author": "税理士ひで | あなたの資産形成に役立つ情報を発信します |",
      "likes": 10,
      "price": 0,
      "tag": "日経平均",
      "url": "https://note.com/hide_taxnote/n/n3be6d06251de"
    },
    {
      "title": "優待　ヤマハ発動機",
      "author": "わたあめ",
      "likes": 3,
      "price": 0,
      "tag": "日本株",
      "url": "https://note.com/unique_acacia893/n/ne88c0de1762a"
    },
    {
      "title": "3月12日(木)19時～20時分〆🎯1日限定：ナイターレース・コロガシマガジン ✨1日で帯(100万円)を掴め👍",
      "author": "⚔AI競艇将軍⚔コロガシ術で1日で帯(100万円)狙い打ち🎯",
      "likes": 3,
      "price": 0,
      "tag": "高配当",
      "url": "https://note.com/ai_yosou_2026/n/n1a4a8ad8ad02"
    },
    {
      "title": "NISA貧乏になるでしょ😅人間だもの",
      "author": "はなぺた",
      "likes": 2,
      "price": 0,
      "tag": "株式投資",
      "url": "https://note.com/pure_phlox589/n/nfa17aceee670"
    },
    {
      "title": "「二番底」を警戒する相場で見えた、日本株の底力",
      "author": "めいだいふ",
      "likes": 1,
      "price": 0,
      "tag": "日本株",
      "url": "https://note.com/merry_alpaca5589/n/nd1d63b2cdcba"
    },
    {
      "title": "配当利回り4.8%、DOE3%導入のホンダ。ヤマハ発動機を手放した私が次に注目した自動車株",
      "author": "ガッチャン",
      "likes": 1,
      "price": 0,
      "tag": "日本株",
      "url": "https://note.com/lively_duck864/n/n8b7f37a2d1ee"
    },
    {
      "title": "自己紹介│株ラボ│はじめてのnote",
      "author": "株ラボ",
      "likes": 1,
      "price": 0,
      "tag": "株式投資",
      "url": "https://note.com/dear_human3058/n/n552e5238a742"
    },
    {
      "title": "「三菱重工が上がった」——で、次はどこが動くの？を視覚的に把握できるサービスを作った",
      "author": "sssssssiiiiinnn",
      "likes": 1,
      "price": 0,
      "tag": "株式投資",
      "url": "https://note.com/sssssssiiiiinnn/n/ne0ff96006414"
    },
    {
      "title": "ガソリン高騰と備蓄放出相場が見ている「次の資金移動」【相場の見方②】",
      "author": "待つ投資家|低回転スイング",
      "likes": 1,
      "price": 0,
      "tag": "日経平均",
      "url": "https://note.com/gentle_rat4564/n/nc0b93d8fbd98"
    },
    {
      "title": "無料版｜3/12㈭ 相場３分メモ｜原油再上昇 × トリプル安",
      "author": "JoyLab",
      "likes": 1,
      "price": 0,
      "tag": "日経平均",
      "url": "https://note.com/joylab/n/n1ba16918c805"
    },
    {
      "title": "【最速日経日報】下落で見るべきは\"コレ\"",
      "author": "諏訪｜日本株研究家",
      "likes": 1,
      "price": 0,
      "tag": "日経平均",
      "url": "https://note.com/fine_lotus986/n/n9f154ab3de52"
    },
    {
      "title": "ガソリン代値上げで考える。日本経済の大きな転換期か？原油暴騰・円安・株価急落で“半世紀ぶりの危機”が迫る！",
      "author": "川淵ゆかり",
      "likes": 1,
      "price": 0,
      "tag": "日経平均",
      "url": "https://note.com/yukarik001/n/n13e3eeccbc07"
    },
    {
      "title": "締め切り30分前💜2時間限定：ナイター🩷コロガシマガジン 🎯🚤💰3月12日(木)19時～20時35分〆",
      "author": "アオイ｜競艇AIで資金を100倍にする方法",
      "likes": 1,
      "price": 0,
      "tag": "高配当",
      "url": "https://note.com/kyoutei_ai_aoi/n/n61fa55758bb2"
    },
    {
      "title": "3月12日(木)日本株振り返り　元気のない相場　#45",
      "author": "ちーち",
      "likes": 0,
      "price": 0,
      "tag": "日本株",
      "url": "https://note.com/kuroirochii/n/n713d39b337aa"
    },
    {
      "title": "【3/12】日経-572円、AI予測が全勝した日の分析【勝率78.6%・累計+56万円】",
      "author": "くじら投資研究所",
      "likes": 0,
      "price": 0,
      "tag": "日本株",
      "url": "https://note.com/marketscope_lab/n/n73580b04f96c"
    },
    {
      "title": "『金利』が上がると『銀行』は儲かるって、本当にそんな単純なの？【2026年3月12日更新】",
      "author": "明日話せる業界ニュース",
      "likes": 0,
      "price": 0,
      "tag": "日本株",
      "url": "https://note.com/toshi3210/n/n3a36a61ae2bb"
    },
    {
      "title": "【2026年3月12日】今日の日経平均株価の流れと結果は？～1分でサクッと読む",
      "author": "守屋 勇希｜立川の資産形成FP",
      "likes": 0,
      "price": 0,
      "tag": "日本株",
      "url": "https://note.com/reterasi/n/neb9db3dd8616"
    },
    {
      "title": "【40代】ゆるデイトレ、仕事の合間に急騰ランキングだけで1万円稼いでイヤホンを買った話",
      "author": "はな｜40代から整える暮らし",
      "likes": 0,
      "price": 0,
      "tag": "日本株",
      "url": "https://note.com/hana_life40/n/na161e1d719c9"
    },
    {
      "title": "43,000円の指値を待っている",
      "author": "子育て投資家",
      "likes": 0,
      "price": 0,
      "tag": "日本株",
      "url": "https://note.com/famous_crab3129/n/n1873bf2f1d2c"
    },
    {
      "title": "これは……やばすぎる。⁉️⁉️⁉️",
      "author": "NAOMA👊投資家👊",
      "likes": 0,
      "price": 0,
      "tag": "日本株",
      "url": "https://note.com/yoshida_punch_/n/n3f1191c7f1d7"
    }
  ],
  "nikkei_headlines": [
    {
      "category": "総合",
      "title": "仙台市、4月に再開発の補助上限撤廃　震災からの立ち遅れ挽回へ",
      "url": "https://www.nikkei.com/article/DGXZQOCC0965R0Z00C26A3000000/",
      "date": "2026-03-12T17:10:58+09:00"
    },
    {
      "category": "総合",
      "title": "九州・沖縄の百貨店販売額、1月0.7%減　春節時期ずれ免税売上高減",
      "url": "https://www.nikkei.com/article/DGXZQOJC11C6G0R10C26A3000000/",
      "date": "2026-03-12T17:10:00+09:00"
    },
    {
      "category": "総合",
      "title": "将棋棋譜の再現動画、配信者に再び賠償命令　東京高裁",
      "url": "https://www.nikkei.com/article/DGXZQOUD10AOL0Q6A310C2000000/",
      "date": "2026-03-12T17:10:00+09:00"
    },
    {
      "category": "総合",
      "title": "キリンビバ、子供向け健康飲料を給食に提供　30年までに300施設",
      "url": "https://www.nikkei.com/article/DGXZQOUC119WU0R10C26A3000000/",
      "date": "2026-03-12T17:09:41+09:00"
    },
    {
      "category": "総合",
      "title": "三菱ケミカルG・旭化成、水島でエチレン減産　ナフサ調達難見据え",
      "url": "https://www.nikkei.com/article/DGXZQOUC122ME0S6A310C2000000/",
      "date": "2026-03-12T17:05:13+09:00"
    },
    {
      "category": "国際",
      "title": "中国全人代、党政治局員2人が異例の欠席　汚職疑いの制服組トップら",
      "url": "https://www.nikkei.com/article/DGXZQOGM097R90Z00C26A3000000/",
      "date": "2026-03-12T17:00:50+09:00"
    },
    {
      "category": "国際",
      "title": "韓国、対米合意履行へ3500億ドル投資法　Google規制も緩和",
      "url": "https://www.nikkei.com/article/DGXZQOGM1232G0S6A310C2000000/",
      "date": "2026-03-12T16:57:56+09:00"
    },
    {
      "category": "国際",
      "title": "中国、2026年「デフレ圧力解消」道筋見えず　乏しい改革",
      "url": "https://www.nikkei.com/article/DGXZQOGM1160W0R10C26A3000000/",
      "date": "2026-03-12T16:53:32+09:00"
    },
    {
      "category": "国際",
      "title": "中国「民族団結」損なう外国人の法的責任追及　全人代で新法可決",
      "url": "https://www.nikkei.com/article/DGXZQOGM097QA0Z00C26A3000000/",
      "date": "2026-03-12T16:44:33+09:00"
    },
    {
      "category": "国際",
      "title": "豪IT大手アトラシアン、1600人を解雇　「AIで必要なスキルが変化」",
      "url": "https://www.nikkei.com/article/DGXZQOGM1211X0S6A310C2000000/",
      "date": "2026-03-12T16:42:13+09:00"
    },
    {
      "category": "テクノロジー",
      "title": "PeopleX、AIを軸にした人材管理システム　「SaaSの死」生き残り図る",
      "url": "https://www.nikkei.com/article/DGXZQOUC123JT0S6A310C2000000/",
      "date": "2026-03-12T15:39:10+09:00"
    },
    {
      "category": "テクノロジー",
      "title": "米エニープレイス、日本進出　テック人材の長期滞在向けアパート賃貸",
      "url": "https://www.nikkei.com/article/DGXZQOGN110GL0R10C26A3000000/",
      "date": "2026-03-12T11:16:08+09:00"
    },
    {
      "category": "テクノロジー",
      "title": "Microsoft、2027年に新型「Xbox」試作機　開発者に提供",
      "url": "https://www.nikkei.com/article/DGXZQOGN1202E0S6A310C2000000/",
      "date": "2026-03-12T07:08:18+09:00"
    },
    {
      "category": "テクノロジー",
      "title": "米テック企業、「半身」のアンソロピック支援　政権と倫理で板挟み",
      "url": "https://www.nikkei.com/article/DGXZQOGN11CN20R10C26A3000000/",
      "date": "2026-03-12T05:53:16+09:00"
    },
    {
      "category": "テクノロジー",
      "title": "世界の生成AI「性格」違う？　政治家評価・プロ野球の予測順位を比較",
      "url": "https://www.nikkei.com/article/DGXZQOUC059XC0V00C26A1000000/",
      "date": "2026-03-12T05:00:00+09:00"
    }
  ],
  "fear_greed": {
    "vix": 25.5,
    "score": 30,
    "rating": "Fear",
    "rating_jp": "恐怖"
  },
  "kabutan_news": [
    {
      "title": "Ｃａｓａ、前期営業が上振れ着地・今期は黒字浮上、5円増配へ",
      "url": "https://kabutan.jp/news/?&b=k202603120043"
    },
    {
      "title": "ヨシックス、今期配当を2円増額修正",
      "url": "https://kabutan.jp/news/?&b=k202603120042"
    },
    {
      "title": "リッジアイ、今期経常を一転19％増益に上方修正・最高益更新へ",
      "url": "https://kabutan.jp/news/?&b=k202603120041"
    },
    {
      "title": "エクサＷｉｚ、今期営業を11％上方修正",
      "url": "https://kabutan.jp/news/?&b=k202603120040"
    },
    {
      "title": "大盛工業、11-1月期(2Q)経常は11％増益",
      "url": "https://kabutan.jp/news/?&b=k202603120039"
    },
    {
      "title": "トーエル、11-1月期(3Q)経常は18％増益",
      "url": "https://kabutan.jp/news/?&b=k202603120038"
    },
    {
      "title": "３ＤＭ、今期経常を4.1倍上方修正・最高益予想を上乗せ",
      "url": "https://kabutan.jp/news/?&b=k202603120037"
    },
    {
      "title": "トミタ電機、今期経常は黒字浮上へ",
      "url": "https://kabutan.jp/news/?&b=k202603120036"
    },
    {
      "title": "新都ＨＤ、前期経常が上振れ着地・今期は32％増益へ",
      "url": "https://kabutan.jp/news/?&b=k202603120034"
    },
    {
      "title": "巴工業、11-1月期(1Q)経常は7％減益で着地",
      "url": "https://kabutan.jp/news/?&b=k202603120033"
    }
  ],
  "tradingview_signals": [
    {
      "code": "4676",
      "score": 0.2,
      "signal_jp": "買い",
      "ma_score": 0.4,
      "osc_score": 0
    },
    {
      "code": "7270",
      "score": -0.536,
      "signal_jp": "強い売り",
      "ma_score": -0.8,
      "osc_score": -0.273
    },
    {
      "code": "4331",
      "score": -0.648,
      "signal_jp": "強い売り",
      "ma_score": -0.933,
      "osc_score": -0.364
    },
    {
      "code": "7172",
      "score": -0.603,
      "signal_jp": "強い売り",
      "ma_score": -0.933,
      "osc_score": -0.273
    },
    {
      "code": "2181",
      "score": -0.512,
      "signal_jp": "強い売り",
      "ma_score": -0.933,
      "osc_score": -0.091
    },
    {
      "code": "3668",
      "score": 0.109,
      "signal_jp": "買い",
      "ma_score": 0.4,
      "osc_score": -0.182
    },
    {
      "code": "7203",
      "score": -0.179,
      "signal_jp": "売り",
      "ma_score": -0.267,
      "osc_score": -0.091
    },
    {
      "code": "8306",
      "score": -0.382,
      "signal_jp": "売り",
      "ma_score": -0.4,
      "osc_score": -0.364
    },
    {
      "code": "6501",
      "score": -0.248,
      "signal_jp": "売り",
      "ma_score": -0.133,
      "osc_score": -0.364
    },
    {
      "code": "9984",
      "score": -0.536,
      "signal_jp": "強い売り",
      "ma_score": -0.8,
      "osc_score": -0.273
    },
    {
      "code": "6758",
      "score": -0.045,
      "signal_jp": "中立",
      "ma_score": 0,
      "osc_score": -0.091
    },
    {
      "code": "9983",
      "score": 0.267,
      "signal_jp": "買い",
      "ma_score": 0.533,
      "osc_score": 0
    },
    {
      "code": "8316",
      "score": -0.382,
      "signal_jp": "売り",
      "ma_score": -0.4,
      "osc_score": -0.364
    },
    {
      "code": "8058",
      "score": 0.242,
      "signal_jp": "買い",
      "ma_score": 0.667,
      "osc_score": -0.182
    },
    {
      "code": "8035",
      "score": -0.088,
      "signal_jp": "中立",
      "ma_score": -0.267,
      "osc_score": 0.091
    },
    {
      "code": "6857",
      "score": 0,
      "signal_jp": "中立",
      "ma_score": 0,
      "osc_score": 0
    }
  ],
  "yahoo_board": [
    {
      "code": "4676",
      "source": "minkabu",
      "target_price": "5,723",
      "individual_rating": "売り",
      "analyst_rating": "中立"
    },
    {
      "code": "7270",
      "source": "minkabu",
      "target_price": "4,167",
      "individual_rating": "買い",
      "analyst_rating": "中立"
    },
    {
      "code": "4331",
      "source": "minkabu",
      "target_price": "846",
      "individual_rating": "買い",
      "analyst_rating": "買い"
    },
    {
      "code": "7172",
      "source": "minkabu",
      "target_price": "1,954",
      "individual_rating": "売り",
      "analyst_rating": "中立"
    },
    {
      "code": "2181",
      "source": "minkabu",
      "target_price": "279",
      "individual_rating": "売り",
      "analyst_rating": "買い"
    },
    {
      "code": "3668",
      "source": "minkabu",
      "target_price": "544",
      "individual_rating": "買い",
      "analyst_rating": "買い"
    }
  ],
  "tdnet_disclosures": [
    {
      "title": "業績予想と実績値との差異に関するお知らせ",
      "url": "https://www.release.tdnet.info/inbs/140120260312580901.pdf"
    },
    {
      "title": "2026年１月期通期連結業績予想と実績値との差異に関するお知らせ",
      "url": "https://www.release.tdnet.info/inbs/140120260312580424.pdf"
    },
    {
      "title": "2026年１月期 決算短信〔日本基準〕（連結）",
      "url": "https://www.release.tdnet.info/inbs/140120260312580343.pdf"
    },
    {
      "title": "2026年１月期 決算説明資料",
      "url": "https://www.release.tdnet.info/inbs/140120260312580427.pdf"
    },
    {
      "title": "期末配当予想の修正（増配）に関するお知らせ",
      "url": "https://www.release.tdnet.info/inbs/140120260312580594.pdf"
    },
    {
      "title": "通期業績予想の修正に関するお知らせ",
      "url": "https://www.release.tdnet.info/inbs/140120260311580135.pdf"
    },
    {
      "title": "2026年７月期　第２四半期（中間期）決算短信〔日本基準〕（非連結）",
      "url": "https://www.release.tdnet.info/inbs/140120260312580373.pdf"
    },
    {
      "title": "当社株式の貸借銘柄選定に関するお知らせ",
      "url": "https://www.release.tdnet.info/inbs/140120260312580411.pdf"
    },
    {
      "title": "2026年７月期連結業績予想の修正に関するお知らせ",
      "url": "https://www.release.tdnet.info/inbs/140120260312580277.pdf"
    },
    {
      "title": "2026年７月期第２四半期（中間期）決算短信〔日本基準〕(連結)",
      "url": "https://www.release.tdnet.info/inbs/140120260310579366.pdf"
    },
    {
      "title": "2026年７月期　第２四半期決算説明資料",
      "url": "https://www.release.tdnet.info/inbs/140120260312580299.pdf"
    },
    {
      "title": "（訂正）「2025 年 12 月期 決算短信〔日本基準〕（連結）」の一部訂正について",
      "url": "https://www.release.tdnet.info/inbs/140120260312580374.pdf"
    },
    {
      "title": "通期連結業績予想の修正（上方修正）に関するお知らせ",
      "url": "https://www.release.tdnet.info/inbs/140120260312580693.pdf"
    },
    {
      "title": "株式会社Exa Frontier Edge（子会社）の設立に関するお知らせ",
      "url": "https://www.release.tdnet.info/inbs/140120260312580735.pdf"
    },
    {
      "title": "2026年７月期 第２四半期（中間期）決算短信【日本基準】（連結）",
      "url": "https://www.release.tdnet.info/inbs/140120260206550847.pdf"
    }
  ],
  "google_news": [
    {
      "title": "12日寄り付き直後の日本株は下落､先行き不透明感強まる - 四季報オンライン",
      "url": "https://news.google.com/rss/articles/CBMiV0FVX3lxTE9jUDRZVUIxQXphclN1NURkeTY5TF9RV0lJV1hoSTZXaWZTUmd6RUpUTGRoVUU4MDRSYnU0MFB2bjJDeFpKLURSUWg1ZkdrNWc3VFhCcE9QQQ?oc=5",
      "published": "Thu, 12 Mar 2026 00:45:00 GMT"
    },
    {
      "title": "対イラン攻撃と日本株想定、DOEを用いた高配当利回り戦略 - マネクリ",
      "url": "https://news.google.com/rss/articles/CBMiVEFVX3lxTE13SE1ScVExMjhTcHdHX29Hb093NVBFMlJBc1V0ZDNkbHl6YTVPQUlQUnlTWWQ1QXIxQmNlSFZ2ak5UYUpDUTlLOEhMUFZBaXp0SE52etIBV0FVX3lxTE5RdU9pZmZpN3lvM05HY1VqaVctMUF5emdLazgwV2ZGV3N6S0hicGRnYWg4SmFobk9JVThRWXg0MWFPMmxKQzZtazFkQUFIY3dWeE9Fd254WQ?oc=5",
      "published": "Wed, 11 Mar 2026 08:20:00 GMT"
    },
    {
      "title": "★本日の【サプライズ決算】速報 (03月12日) - かぶたん",
      "url": "https://news.google.com/rss/articles/CBMiYEFVX3lxTE9nV2RrRHpKRHBrUm1uWjlBdXpPWjZQcU1NVEtiQmZWQTBrSW1lekRCaFUzWFloUTc1NVd5UnVJNHAxR1oybWdsQUdEd3BJZmdyNkxHNEk5R3pqTkxteTh2YQ?oc=5",
      "published": "Thu, 12 Mar 2026 08:06:57 GMT"
    },
    {
      "title": "任天堂・ソフトバンクG大幅高/公開価格割れ続くIPO、3月は…/日経平均続伸【今日の注目株＆日本株市場見通し】「デイリーZAi」3月11日号 - ダイヤモンド・",
      "url": "https://news.google.com/rss/articles/CBMiU0FVX3lxTE54UF9WQ1BhVUFiTE5Zem1mbDR4c19TSk9XRU9TbUNQVGRJVGFvdDFpOGNPV0k3REV4enNqLTNpUjZDN29BV0FtN0hoMVJjbUdQYWEw?oc=5",
      "published": "Wed, 11 Mar 2026 10:04:21 GMT"
    },
    {
      "title": "「株式」ADR日本株ランキング～全般売り優勢、シカゴは大阪日中比425円安の54775円(フィスコ) - Yahoo!ファイナンス",
      "url": "https://news.google.com/rss/articles/CBMihwFBVV95cUxOamdVQXd5a0NkeDE3M2lHaWhmcmRlY2hDRTRrTnhxNjgwWkVMSWs1S0VXRlJNNnFNRTB1WVRGS0NlbS1mc0pMR3hXNHVFMzVfU0xncDQ4bmlIN0Y5clBTcDNaODV5MWl3ZmJOWEZhWHJBZXgydVRka01yMWhEQjk0eGpWeXh0R3M?oc=5",
      "published": "Thu, 12 Mar 2026 00:06:00 GMT"
    },
    {
      "title": "100億円投資家テスタさんの保有50銘柄「日本株42銘柄で28.6億円分」配当利回りは〈ホンマでっか！？TVきょうテスタさん出演〉 - AERA DIGITAL",
      "url": "https://news.google.com/rss/articles/CBMiWkFVX3lxTE9RSmdBOHJuME1DTDgtUUdna0J2dElwcXYxcjdwdXpqZFZ3eVo5MzNQb3FENENYT2JsRmMtd1lNWjVVS0hFN04ybzE5TF9ILXhlQmpSeU9zNlRfdw?oc=5",
      "published": "Wed, 11 Mar 2026 12:00:00 GMT"
    },
    {
      "title": "日本株は続伸へ、米半導体株高や原油の落ち着き好感－電機や金融買い - Bloomberg",
      "url": "https://news.google.com/rss/articles/CBMid0FVX3lxTFBrZWFBZGllYldzMlJFSVlWTlhwZmtodTIxWGwySHVkTmhEUHNSVk8yNVBoeFZPYnJYdEtGVEZNSUhnbm8wN192d2E4cnJlT2wzQ3hqTm05enpJdG1BaFJGcHR0cVVla19QY1laV0o5LTZGZUhacEpJ?oc=5",
      "published": "Tue, 10 Mar 2026 22:51:20 GMT"
    },
    {
      "title": "日本株はイラン情勢の緊迫化を乗り越えるか QUICK月次調査・株式 - QUICK Money World",
      "url": "https://news.google.com/rss/articles/CBMiVkFVX3lxTE4wcm9zQ3UyVjFrX01STXF1eEJuaF9ZTkdGeWRxZWIyckE2LWZkdERtYWUwR3V4a2x0OGFxSXBGQjJhMmdYbzZZdlpPOW9OS2FVWWJUSXNn?oc=5",
      "published": "Mon, 09 Mar 2026 08:46:47 GMT"
    },
    {
      "title": "【新NISA】3月配当取りを狙える、注目の日本株「連続増配株5選」を実名公開 - 現代ビジネス",
      "url": "https://news.google.com/rss/articles/CBMiWEFVX3lxTFBzZkRzLVhhdE56X2JaelgyRDU2Y2tPblh2ZXNEVkxoYjhsQ01yYzgybS0tMnRhY3ZLVnp1T3JkeFlKRXZwb3RlVFhXOXVSOF9OckEyNGdvbEQ?oc=5",
      "published": "Mon, 09 Mar 2026 04:52:52 GMT"
    },
    {
      "title": "ニデックの株価が一時7.9%高 香港オアシスが6.74%保有 - 日本経済新聞",
      "url": "https://news.google.com/rss/articles/CBMibEFVX3lxTE1GZF9qek90OUpDLXMzRWlHVkpzN2c0Y0pVMnUteWgxSDZMTWFaeXp1bFBKRk9raVZyY0JING5hd09COEtIakdhMkI1RzJGLXpyWXhRNmxWaHdlSXc0cE9OdzB6eGthNmx1VXBVUA?oc=5",
      "published": "Thu, 12 Mar 2026 01:23:41 GMT"
    },
    {
      "title": "日経平均終値572円安、物価高と景気減速を警戒 「半値戻し」遠のく - 日本経済新聞",
      "url": "https://news.google.com/rss/articles/CBMibEFVX3lxTE51VjNxRFlYVWQ1SjZhbWNndTVuUlB3RmtERUJzc2tiZTN2TklDZWhUcUV1QUZzbU9EOUJ4R21JcXBVT3pIaU1Xdkduc2FNWFBXaWFIOHp3eU1xT2M3RzkwQjdRbDdIM2lvZGJBcw?oc=5",
      "published": "Thu, 12 Mar 2026 02:51:36 GMT"
    },
    {
      "title": "【市況】 伊藤智洋が読む「日経平均株価・短期シナリオ」 (3月12日記） - かぶたん",
      "url": "https://news.google.com/rss/articles/CBMiYEFVX3lxTE00SVhXSmlWWXoycmo1YVMyQ2tqNEhWY0w2Z1RQRmhMbE5mYXB0N3h4VUZ3Wl9Yb2tDVXZQMkU3TVczLV9oRXhrSlR4T25LUFducGp0V0NKd0ZsUlpHX29JbA?oc=5",
      "published": "Wed, 11 Mar 2026 23:11:45 GMT"
    },
    {
      "title": "日経平均テクニカル： 3日ぶり反落、5日線と25日線が下向き転換(フィスコ) - Yahoo!ファイナンス",
      "url": "https://news.google.com/rss/articles/CBMihwFBVV95cUxNUWp3c2xXT0twU1lnNFlvQTNMYlBMVVFYRGNjYkh4bWRBZVFsTThVZ3FJNGxrRzBSaWZUeW56WS00TUZ5ejVtMHFyMml3NWp2cWlkZ1VKbzEwV1N1NUt1YzBWQkJGallZVElWV1ZEaGMzaHY3R1lrTURCalZPaXVldGNfSGJ6N3M?oc=5",
      "published": "Thu, 12 Mar 2026 09:15:00 GMT"
    },
    {
      "title": "「日経225先物」手口情報（12日夜間） ABNクリアリン証券取引高トップ、3月限8725枚 | 市況 - 株探ニュース - かぶたん",
      "url": "https://news.google.com/rss/articles/CBMiYkFVX3lxTE1vUlZsTlVxZk4zRWd0MFRHSXoxb0JCZXRDOS1iSEoxU2xpUDVqSF9oc0t1V0R1V2U4UGlEcGppdEdkWnVqYjN6SGJVVlU3Z3NCUi1rUE1zYThKbWhnYzBRdVZn?oc=5",
      "published": "Thu, 12 Mar 2026 09:01:19 GMT"
    },
    {
      "title": "「日経225ミニ」手口情報（12日日中） ソシエテジェネラル証券取引高トップ、3月限4万2085枚 | 市況 - 株探ニュース - かぶたん",
      "url": "https://news.google.com/rss/articles/CBMiYkFVX3lxTE5zaHdjb1BDM0lIUlc1eERReW54YllzV1Y5UVh3SXh2SExJSzMtOE11M3NxQU1SRUZwN2JEczBBUGxQeGR4WU9ia0JTUFVFd0FYTERpM0dCSTBlWFlUY3Q5QW5R?oc=5",
      "published": "Thu, 12 Mar 2026 09:01:14 GMT"
    }
  ]
}